uun_guardman/__init__.py
uun_guardman/data/sample-config.json
uun_guardman/data/start.sh
uun_guardman/data/systemd.service
uun_guardman/modules/GuardMan.py
uun_guardman/modules/__init__.py
uun_guardman-0.1.6.data/scripts/uun-guardman
uun_guardman-0.1.6.data/scripts/uun-guardman-install
uun_guardman-0.1.6.data/scripts/uun-guardman-setup
uun_guardman-0.1.6.dist-info/LICENSE.md
uun_guardman-0.1.6.dist-info/METADATA
uun_guardman-0.1.6.dist-info/WHEEL
uun_guardman-0.1.6.dist-info/top_level.txt
uun_guardman-0.1.6.dist-info/RECORD
